motion_pipeline/__init__.py
motion_pipeline/version.py
motion_pipeline/tests/__init__.py
motion_pipeline/tests/test_version.py
motion_pipeline-0.1.0.dist-info/METADATA
motion_pipeline-0.1.0.dist-info/RECORD
motion_pipeline-0.1.0.dist-info/WHEEL
motion_pipeline-0.1.0.dist-info/top_level.txt
