Metadata-Version: 2.1
Name: motion-pipeline
Version: 0.1.0
Summary: Frontend and recording management pipeline for the Motion video motion detection project
Home-page: https://github.com/jantman/motion-pipeline
Author: Jason Antman
Author-email: jason@jasonantman.com
License: UNKNOWN
Keywords: motion video frontend detection
Platform: UNKNOWN
Classifier: Development Status :: 1 - Planning
Classifier: License :: OSI Approved :: GNU Affero General Public License v3 or later (AGPLv3+)
Classifier: Programming Language :: Python
Classifier: Programming Language :: Python :: 3
Classifier: Programming Language :: Python :: 3.4
Classifier: Programming Language :: Python :: 3.5
Classifier: Programming Language :: Python :: 3.6
Requires-Dist: boto3
